gaminet/__init__.py
gaminet/gaminet.py
gaminet/interpret.py
gaminet/layers.py
gaminet/utils.py
gaminet/lib/lib_ebmcore_linux_x64.so
gaminet/lib/lib_ebmcore_mac_x64.dylib
gaminet/lib/lib_ebmcore_win_x64.dll
gaminet-0.6.1.dist-info/LICENSE
gaminet-0.6.1.dist-info/METADATA
gaminet-0.6.1.dist-info/WHEEL
gaminet-0.6.1.dist-info/top_level.txt
gaminet-0.6.1.dist-info/RECORD
