Metadata-Version: 2.1
Name: gaminet
Version: 0.6.1
Summary: Explainable Neural Networks based on Generalized Additive Models with Structured Interactions
Home-page: https://github.com/ZebinYang/GAMINet
Author: Zebin Yang
Author-email: yangzb2010@connect.hku.hk
License: GPL
Platform: UNKNOWN
License-File: LICENSE
Requires-Dist: matplotlib (>=3.1.3)
Requires-Dist: tensorflow (>=2.0.0)
Requires-Dist: numpy (>=1.15.2)
Requires-Dist: pandas (>=0.19.2)
Requires-Dist: scikit-learn (>=0.23.0)
Requires-Dist: tensorflow-lattice (>=2.0.8)
